rprintlib/__init__.py
rprintlib/rpmain.py
rprintlib-1.3.dist-info/LICENSE
rprintlib-1.3.dist-info/METADATA
rprintlib-1.3.dist-info/WHEEL
rprintlib-1.3.dist-info/top_level.txt
rprintlib-1.3.dist-info/RECORD
