Metadata-Version: 2.1
Name: rprintlib
Version: 1.3
Summary: Pure python custom print implementation
Home-page: https://wirtos.github.io/Rprint/
Author: Wirtos_new
Author-email: Wirtos.new@gmail.com
License: UNKNOWN
Project-URL: Source Code, https://github.com/Wirtos/Rprint
Keywords: print rprint Rprint rprintlib
Platform: UNKNOWN
Classifier: Programming Language :: Python :: 3
Classifier: License :: OSI Approved :: MIT License
Classifier: Operating System :: OS Independent
